{
  "recipes": [
    {
      "firstRow": {
        "firstItem": "minecolonies/cactus_planks",
        "secondItem": "",
        "thirdItem": ""
      },
      "secondRow": {
        "firstItem": "minecolonies/cactus_planks",
        "secondItem": "minecolonies/cactus_planks",
        "thirdItem": ""
      },
      "thirdRow": {
        "firstItem": "minecolonies/cactus_planks",
        "secondItem": "minecolonies/cactus_planks",
        "thirdItem": "minecolonies/cactus_planks"
      },
      "product": "minecolonies/cactus_stairs",
      "amount": "4"
    }
  ]
}